FNA_DB/DBClient.py
FNA_DB/__init__.py
fna_db-0.1.0.dist-info/licenses/LICENSE
fna_db-0.1.0.dist-info/METADATA
fna_db-0.1.0.dist-info/WHEEL
fna_db-0.1.0.dist-info/top_level.txt
fna_db-0.1.0.dist-info/RECORD
