Metadata-Version: 2.4
Name: FNA_DB
Version: 0.1.0
Summary: Client für den FNA-DBServer
Home-page: https://gitlab.gras-it.de/bsapp/fieldnet-ampel/fna-dbclient
Author: Hyabusa1990
Classifier: Programming Language :: Python :: 3
Classifier: License :: OSI Approved :: MIT License
Classifier: Operating System :: OS Independent
Requires-Python: >=3.6
License-File: LICENSE
Dynamic: author
Dynamic: classifier
Dynamic: description
Dynamic: description-content-type
Dynamic: home-page
Dynamic: license-file
Dynamic: requires-python
Dynamic: summary
